{
  "resources": [
    {
      "path": "data.csv",
      "name": "data",
      "profile": "tabular-data-resource",
      "scheme": "file",
      "format": "csv",
      "hashing": "md5",
      "encoding": "utf-8",
      "schema": {
        "fields": [
          {
            "name": "Year",
            "type": "integer",
            "title": "Year"
          },
          {
            "name": "Series",
            "type": "string",
            "constraints": {
              "enum": [
                "Proportion of forest area within legally established protected areas",
                ""
              ]
            },
            "title": "Series"
          },
          {
            "name": "Units",
            "type": "string",
            "constraints": {
              "enum": [
                "%",
                ""
              ]
            },
            "title": "Units"
          },
          {
            "name": "Value",
            "type": "number",
            "title": "Value"
          }
        ]
      }
    }
  ],
  "profile": "data-package",
  "name": "15-2-1",
  "title": "Progress towards sustainable forest management"
}