{"computation_units":"mln. USD","data_non_statistical":false,"graph_title":"Foreign direct investments (FDI)","graph_type":"line","indicator":"17.3.1.a","indicator_name":"Foreign direct investments (FDI)","indicator_sort_order":"17-03-01-0a","national_indicator_description":"The foreign direct investment is the acquisition by a resident(s) of one country 10% or more of the voting  power in the capital of another country's resident organization, all financial claims and liabilities with those investors and related organizations, as well as the share of those investors in organization profit. Direct investments are implemented: 1) In the authorized and emission  capital, in the form of bonds, shares, equity participation, i.e., when another organization is managing the voting shares (common stocks, interests, shares) of not less than 50% (subsidiary) and when another organization owns 10-50% of the voting power (affiliated company), 2) In the direct investor's share to the other elements of entity's own capital, 3) In debt instruments. out in form of bonds, other securities (excepting shares), credits, loans, deposits.","national_geographical_coverage":"Armenia","computation_calculations":"The calculations are carried out in accordance with the filling procedure specified in the statistical reporting form","comments_limitations":"The main sources of data collection are the foreign investments and foreign investment implementing organizations, as well as data and additional calculations received from RA Central Bank on indicators of foreign investments. The data collection is implemented by the statistical reporting form in accordance with the Annual and Five Year Statistical Programs (https://www.armstat.am/am/?nid=80&id=2271). ","published":true,"reporting_status":"complete","sdg_goal":"17","source_active_1":true,"source_organisation_1":"Armstat","source_active_2":true,"source_organisation_2":"Central Bank of Armenia","tags":["National"],"target_id":"17.3","page_content":"","national_metadata_updated_date":"2020-11-15","national_data_updated_date":"2022-06-07","national_metadata_update_url_text":"2020-11-15: see changes on GitHub","national_metadata_update_url":"https://github.com/armstat/sdg-data-armenia/commit/e9f0ab768ee1a1299b98539f0de1d9fa2d207e64","national_data_update_url_text":"2022-06-07: see changes on GitHub","national_data_update_url":"https://github.com/armstat/sdg-data-armenia/commit/dcc23e4853404c3c991cd4088b071f7bf3e7521f"}