{"computation_units":"data.persons","data_non_statistical":false,"graph_title":"meta.name-16-7-1-c","graph_type":"line","indicator":"16.7.1-c","indicator_name":"meta.name-16-7-1-c","indicator_sort_order":"16-07-1-c","national_indicator_description":"meta.description-16-7-1-c","national_geographical_coverage":"\u0410\u0440\u043c\u0435\u043d\u0438\u044f","computation_definitions":"meta.definitions-16-7-1-c","computation_calculations":"meta.calculations-16-7-1-c","comments_limitations":"meta.comments-16-7-1-c","published":true,"reporting_status":"complete","sdg_goal":"16","source_active_1":true,"source_organisation_1":"\u0421\u0443\u0434\u0435\u0431\u043d\u044b\u0439 \u0434\u0435\u043f\u0430\u0440\u0442\u0430\u043c\u0435\u043d\u0442 \u0420\u0410","tags":["\u043d\u0430\u0446\u0438\u043e\u043d\u0430\u043b\u044c\u043d\u044b\u0439"],"target_id":"16.1","page_content":"","national_metadata_updated_date":"2026-02-11","indicator_number":"16.7.1.c","target_number":"16.7","goal_number":"16"}