{"Year":[2015,2016,2017,2018,2019,2015,2016,2017,2018,2019,2015,2016,2017,2018,2019,2015,2016,2017,2018,2019,2015,2016,2017,2018,2019,2015,2016,2017,2018,2019,2015,2016,2017,2018,2019,2015,2016,2017,2018,2019,2015,2016,2017,2018,2019,2015,2016,2017,2018,2019,2015,2016,2017,2018,2019,2015,2016,2017,2018,2019,2015,2016,2017,2018,2019,2015,2016,2017,2018,2019,2015,2016,2017,2018,2019,2015,2016,2017,2018,2019,2015,2016,2017,2018,2019,2015,2016,2017,2018,2019],"Units":["person","person","person","person","person","person","person","person","person","person","person","person","person","person","person","person","person","person","person","person","person","person","person","person","person","person","person","person","person","person","person","person","person","person","person","person","person","person","person","person","person","person","person","person","person","person","person","person","person","person","person","person","person","person","person","person","person","person","person","person","person","person","person","person","person","person","person","person","person","person","person","person","person","person","person","person","person","person","person","person","person","person","person","person","person","person","person","person","person","person"],"Sex":[null,null,null,null,null,"male","male","male","male","male","female","female","female","female","female",null,null,null,null,null,"male","male","male","male","male","female","female","female","female","female",null,null,null,null,null,"male","male","male","male","male","female","female","female","female","female",null,null,null,null,null,"male","male","male","male","male","female","female","female","female","female",null,null,null,null,null,"male","male","male","male","male","female","female","female","female","female",null,null,null,null,null,"male","male","male","male","male","female","female","female","female","female"],"Age":[null,null,null,null,null,null,null,null,null,null,null,null,null,null,null,"up to 1 year old","up to 1 year old","up to 1 year old","up to 1 year old","up to 1 year old","up to 1 year old","up to 1 year old","up to 1 year old","up to 1 year old","up to 1 year old","up to 1 year old","up to 1 year old","up to 1 year old","up to 1 year old","up to 1 year old","aged 1-6 years","aged 1-6 years","aged 1-6 years","aged 1-6 years","aged 1-6 years","aged 1-6 years","aged 1-6 years","aged 1-6 years","aged 1-6 years","aged 1-6 years","aged 1-6 years","aged 1-6 years","aged 1-6 years","aged 1-6 years","aged 1-6 years","aged 7-9 years","aged 7-9 years","aged 7-9 years","aged 7-9 years","aged 7-9 years","aged 7-9 years","aged 7-9 years","aged 7-9 years","aged 7-9 years","aged 7-9 years","aged 7-9 years","aged 7-9 years","aged 7-9 years","aged 7-9 years","aged 7-9 years","aged 10-15 years","aged 10-15 years","aged 10-15 years","aged 10-15 years","aged 10-15 years","aged 10-15 years","aged 10-15 years","aged 10-15 years","aged 10-15 years","aged 10-15 years","aged 10-15 years","aged 10-15 years","aged 10-15 years","aged 10-15 years","aged 10-15 years","aged 16-17 years","aged 16-17 years","aged 16-17 years","aged 16-17 years","aged 16-17 years","aged 16-17 years","aged 16-17 years","aged 16-17 years","aged 16-17 years","aged 16-17 years","aged 16-17 years","aged 16-17 years","aged 16-17 years","aged 16-17 years","aged 16-17 years"],"Value":[78,64,45,52,81,38,39,21,25,41,40,25,24,27,40,11,6,2,4,7,6,5,0,1,4,5,1,2,3,3,32,19,15,21,21,15,11,8,11,13,17,8,7,10,8,14,13,7,8,20,6,6,4,5,7,8,7,3,3,13,18,20,15,11,19,8,15,6,5,10,10,5,9,6,9,3,6,6,2,14,3,2,3,0,7,0,4,3,2,7]}