{"data":{"Year":[2020,2021,2022,2023,2020,2021,2022,2023,2020,2021,2022,2023,2020,2021,2022,2023,2020,2021,2022,2023,2020,2021,2022,2023],"Units":["%","%","%","%","%","%","%","%","%","%","%","%","%","%","%","%","%","%","%","%","%","%","%","%"],"Sex":["male","male","male","male","female","female","female","female",null,null,null,null,null,null,null,null,null,null,null,null,null,null,null,null],"Age":[null,null,null,null,null,null,null,null,"aged 15- 24","aged 15- 24","aged 15-24","aged 15- 24","aged 25- 64","aged 25- 64","aged 25- 64","aged 25- 64","aged 65+","aged 65+","aged 65+","aged 65+",null,null,null,null],"Type":[null,null,null,null,null,null,null,null,null,null,null,null,null,null,null,null,null,null,null,null,"disabled","disabled","disabled","disabled"],"Value":[81.2,77.0,74.0,72.1,79.1,76.6,74.2,71.6,79.2,76.1,74.6,72.6,80.8,76.7,73.9,71.4,77.6,78.4,72.3,70.1,78.1,78.5,75.6,71.7]},"edges":[]}